environment_framework/__init__.py
environment_framework/estimator.py
environment_framework/game.py
environment_framework/gym.py
environment_framework/ilevel.py
environment_framework/level.py
environment_framework/observer.py
environment_framework/py.typed
environment_framework/pygame_wrapper.py
environment_framework/simulator.py
environment_framework/visualizer.py
environment_framework-0.3.0.dist-info/METADATA
environment_framework-0.3.0.dist-info/WHEEL
environment_framework-0.3.0.dist-info/licenses/LICENSE
environment_framework-0.3.0.dist-info/RECORD
