Metadata-Version: 2.3
Name: environment-framework
Version: 0.3.0
Summary: Loose building blocks to create agent-environment loops.
Project-URL: Source, https://github.com/crzdg/environment-framework
Author: Reto Barmettler
License-Expression: MIT
License-File: LICENSE
Classifier: Development Status :: 3 - Alpha
Classifier: Operating System :: OS Independent
Classifier: Programming Language :: Python :: 3 :: Only
Classifier: Programming Language :: Python :: 3.8
Classifier: Programming Language :: Python :: 3.9
Classifier: Programming Language :: Python :: 3.10
Classifier: Programming Language :: Python :: 3.11
Requires-Python: >=3.8
Requires-Dist: gymnasium>=0.26
Requires-Dist: numpy
Requires-Dist: pygame
Provides-Extra: ci
Requires-Dist: genbadge[all]; extra == 'ci'
Requires-Dist: hatch; extra == 'ci'
Requires-Dist: hatch-regex-commit; extra == 'ci'
Provides-Extra: dev
Requires-Dist: hatch; extra == 'dev'
Provides-Extra: extra
Requires-Dist: ipywidgets; extra == 'extra'
Requires-Dist: jupyterlab; extra == 'extra'
Requires-Dist: jupytext; extra == 'extra'
Requires-Dist: opencv-python; extra == 'extra'
Requires-Dist: sb3-contrib>=2.0.0a1; extra == 'extra'
Requires-Dist: tqdm; extra == 'extra'
Provides-Extra: lint
Requires-Dist: pylint; extra == 'lint'
Provides-Extra: style
Requires-Dist: black; extra == 'style'
Requires-Dist: isort; extra == 'style'
Provides-Extra: test
Requires-Dist: pytest; extra == 'test'
Requires-Dist: pytest-cov; extra == 'test'
Requires-Dist: pytest-mock; extra == 'test'
Provides-Extra: type
Requires-Dist: mypy; extra == 'type'
Requires-Dist: types-pyyaml; extra == 'type'
